topsis/__init__.py
Topsis_Akshat-1.0.0.dist-info/LICENSE
Topsis_Akshat-1.0.0.dist-info/METADATA
Topsis_Akshat-1.0.0.dist-info/WHEEL
Topsis_Akshat-1.0.0.dist-info/top_level.txt
Topsis_Akshat-1.0.0.dist-info/RECORD
