Metadata-Version: 2.1
Name: Topsis-Akshat
Version: 1.0.0
Summary: A Python package implementing TOPSIS technique.
Home-page: https://github.com/akshat0703/Topsis-Akshat.git
Author: Akshat Gupta
Author-email: aksgupta0001@gmail.com
License: MIT
Platform: UNKNOWN
Classifier: License :: OSI Approved :: MIT License
Classifier: Programming Language :: Python :: 3.6
Classifier: Programming Language :: Python :: 3.7
Classifier: Programming Language :: Python :: 3.8
Classifier: Programming Language :: Python :: 3.9
License-File: LICENSE
